CHANGELOG.md
cointainer_scraper_ecb/__init__.py
cointainer_scraper_ecb/coins.py
cointainer_scraper_ecb/data/countries.json
cointainer_scraper_ecb/data/LICENSE
cointainer_scraper_ecb/py.typed
cointainer_scraper_ecb-0.1.3.dist-info/LICENSE
cointainer_scraper_ecb-0.1.3.dist-info/WHEEL
cointainer_scraper_ecb-0.1.3.dist-info/METADATA
cointainer_scraper_ecb-0.1.3.dist-info/RECORD
