Metadata-Version: 2.1
Name: cointainer-scraper-ecb
Version: 0.1.3
Summary: Cointainer component for scraping coins from the ECB Website.
Home-page: https://github.com/cointainer/cointainer-scraper-ecb
License: Apache-2.0
Keywords: scraper,ecb,coins,collectables
Author: B4rtware
Author-email: 34386047+B4rtware@users.noreply.github.com
Requires-Python: >=3.9,<4.0
Classifier: License :: OSI Approved :: Apache Software License
Classifier: Natural Language :: English
Classifier: Operating System :: OS Independent
Classifier: Programming Language :: Python
Classifier: Programming Language :: Python :: 3
Classifier: Programming Language :: Python :: 3.9
Classifier: Programming Language :: Python :: 3.10
Classifier: Topic :: Internet
Classifier: Topic :: Software Development :: Libraries :: Python Modules
Classifier: Typing :: Typed
Requires-Dist: beautifulsoup4 (>=4.10.0,<5.0.0)
Requires-Dist: dateparser (>=1.1.4,<2.0.0)
Requires-Dist: pycountry (>=22.3.5,<23.0.0)
Requires-Dist: requests (>=2.27.1,<3.0.0)
Project-URL: Repository, https://github.com/cointainer/cointainer-scraper-ecb
